screen_manager-0.1.0.dist-info/licenses/LICENSE
screen_session_manager/ScreenSessionManager.py
screen_session_manager/__init__.py
screen_session_manager/__main__.py
screen_session_manager/__version__.py
screen_session_manager/agent_id_detection.py
screen_session_manager/cli.py
screen_session_manager/mcp_server.py
screen_session_manager/prompt_detection.py
screen_manager-0.1.0.dist-info/METADATA
screen_manager-0.1.0.dist-info/WHEEL
screen_manager-0.1.0.dist-info/top_level.txt
screen_manager-0.1.0.dist-info/RECORD
