Metadata-Version: 2.4
Name: screen-manager
Version: 0.1.0
Summary: Screen session manager with MCP support
Author-email: Yusuke Watanabe <yusuke.watanabe@scitex.ai>
Maintainer-email: Yusuke Watanabe <yusuke.watanabe@scitex.ai>
License-Expression: MIT
Project-URL: Homepage, https://github.com/Yusuke Watanabe/screen-manager
Project-URL: Repository, https://github.com/Yusuke Watanabe/screen-manager
Project-URL: Documentation, https://github.com/Yusuke Watanabe/screen-manager
Keywords: debugging,ipdb,multi-agent,mcp,screen,session-management,conditional-debugging,AI-agents
Classifier: Development Status :: 4 - Beta
Classifier: Intended Audience :: Developers
Classifier: Operating System :: OS Independent
Classifier: Programming Language :: Python :: 3
Classifier: Programming Language :: Python :: 3.11
Classifier: Programming Language :: Python :: 3.12
Classifier: Topic :: Software Development :: Debuggers
Classifier: Topic :: System :: Shells
Classifier: Topic :: Communications
Requires-Python: >=3.11
License-File: LICENSE
Requires-Dist: cipdb>=0.1.0
Requires-Dist: ipdb>=0.13.0
Requires-Dist: fastmcp>=2.0.0
Requires-Dist: pexpect>=4.8.0
Requires-Dist: typing-extensions>=4.0.0
Requires-Dist: aiofiles>=23.0.0
Requires-Dist: pytest>=8.0.0
Requires-Dist: pytest-cov>=5.0.0
Requires-Dist: pytest-xdist>=3.0.0
Requires-Dist: pytest-testmon>=2.0.0
Provides-Extra: dev
Requires-Dist: ruff>=0.7.0; extra == "dev"
Requires-Dist: mypy>=1.13.0; extra == "dev"
Requires-Dist: pytest-cov>=5.0.0; extra == "dev"
Requires-Dist: pytest-json-report>=1.5.0; extra == "dev"
Requires-Dist: pytest-asyncio>=0.24.0; extra == "dev"
Requires-Dist: pytest-watch>=4.2.0; extra == "dev"
Requires-Dist: pre-commit>=3.5.0; extra == "dev"
Requires-Dist: build>=1.0.0; extra == "dev"
Requires-Dist: twine>=5.0.0; extra == "dev"
Dynamic: license-file
